tsunami_ip_utils/__init__.py
tsunami_ip_utils/_error.py
tsunami_ip_utils/comparisons.py
tsunami_ip_utils/config.py
tsunami_ip_utils/input_files/MG_reader.inp
tsunami_ip_utils/input_files/generate_perturbed_library.inp
tsunami_ip_utils/input_files/tsunami_ip_base_input.inp
tsunami_ip_utils/input_files/tsunami_ip_uncertainty_contributions.inp
tsunami_ip_utils/integral_indices.py
tsunami_ip_utils/perturbations.py
tsunami_ip_utils/readers.py
tsunami_ip_utils/utils.py
tsunami_ip_utils/viz/__init__.py
tsunami_ip_utils/viz/_bar_plot.py
tsunami_ip_utils/viz/_base_plotter.py
tsunami_ip_utils/viz/assets/resize.js
tsunami_ip_utils/viz/assets/shutdown.js
tsunami_ip_utils/viz/css/matrix_plot.css
tsunami_ip_utils/viz/matrix_plot.py
tsunami_ip_utils/viz/pie_plot.py
tsunami_ip_utils/viz/plot_utils.py
tsunami_ip_utils/viz/scatter_plot.py
tsunami_ip_utils/viz/viz.py
tsunami_ip_utils/xs.py
tsunami_ip_utils-0.1.2.dist-info/WHEEL
tsunami_ip_utils-0.1.2.dist-info/METADATA
tsunami_ip_utils-0.1.2.dist-info/LICENSE
tsunami_ip_utils-0.1.2.dist-info/RECORD
