Metadata-Version: 2.1
Name: tsunami-ip-utils
Version: 0.1.2
Summary: A tool for visualizing similarity data from the SCALE code: TSUNAMI-IP
License: MIT
Author: Matthew Louis
Author-email: matthewlouis31@gmail.com
Requires-Python: >=3.8,<4.0
Classifier: License :: OSI Approved :: MIT License
Classifier: Programming Language :: Python :: 3
Classifier: Programming Language :: Python :: 3.8
Classifier: Programming Language :: Python :: 3.9
Classifier: Programming Language :: Python :: 3.10
Classifier: Programming Language :: Python :: 3.11
Requires-Dist: IPython
Requires-Dist: dash
Requires-Dist: flask
Requires-Dist: h5py
Requires-Dist: kaleido
Requires-Dist: matplotlib
Requires-Dist: openpyxl
Requires-Dist: pandas
Requires-Dist: plotly (>=5.22.0,<5.23.0)
Requires-Dist: pyprojroot
Requires-Dist: pytest
Requires-Dist: pytest-mpl
Requires-Dist: pyyaml
Requires-Dist: scipy
Requires-Dist: selenium
Requires-Dist: tqdm
Requires-Dist: uncertainties
Requires-Dist: webdriver-manager
Project-URL: Documentation, https://mlouis9.github.io/tsunami_ip_utils
Project-URL: Homepage, https://github.com/mlouis9/tsunami_ip_utils
Project-URL: Issues, https://github.com/mlouis9/tsunami_ip_utils/issues
